websnapshot/__init__.py
websnapshot/__main__.py
websnapshot-0.1.14.dist-info/entry_points.txt
websnapshot-0.1.14.dist-info/WHEEL
websnapshot-0.1.14.dist-info/METADATA
websnapshot-0.1.14.dist-info/RECORD
